ml_init/__init__.py
ml_init-0.6.0.dist-info/WHEEL
ml_init-0.6.0.dist-info/METADATA
ml_init-0.6.0.dist-info/RECORD
