Metadata-Version: 2.1
Name: ml-init
Version: 0.6.0
Summary: Install the main ML libraries
License: MIT
Author: Alberto Rubiales
Author-email: al.rubiales.b@gmail.com
Requires-Python: >=3.9,<=3.11
Classifier: License :: OSI Approved :: MIT License
Classifier: Programming Language :: Python :: 3
Classifier: Programming Language :: Python :: 3.10
Classifier: Programming Language :: Python :: 3.9
Requires-Dist: black (>=21.12b0,<22.0)
Requires-Dist: datasets (>=1.17.0,<2.0.0)
Requires-Dist: flake8 (>=4.0.1,<5.0.0)
Requires-Dist: hdbscan (>=0.8.27,<0.9.0)
Requires-Dist: imbalanced-learn (>=0.9.0,<0.10.0)
Requires-Dist: jupyter (>=1.0.0,<2.0.0)
Requires-Dist: lightgbm (>=3.3.2,<4.0.0)
Requires-Dist: matplotlib (>=3.5.1,<4.0.0)
Requires-Dist: mlflow (>=1.22.0,<2.0.0)
Requires-Dist: notebook (>=6.4.7,<7.0.0)
Requires-Dist: numba (==0.53)
Requires-Dist: numpy (==1.22.0)
Requires-Dist: openpyxl (>=3.0.9,<4.0.0)
Requires-Dist: optuna (>=2.10.0,<3.0.0)
Requires-Dist: plotly (>=5.5.0,<6.0.0)
Requires-Dist: rouge-score (>=0.0.4,<0.0.5)
Requires-Dist: scikit-learn (>=1.0.2,<2.0.0)
Requires-Dist: scikit-surprise (>=1.1.1,<2.0.0)
Requires-Dist: scipy (>=1.7.3,<2.0.0)
Requires-Dist: seaborn (>=0.11.2,<0.12.0)
Requires-Dist: sentence-transformers (>=2.1.0,<3.0.0)
Requires-Dist: statsmodels (>=0.13.1,<0.14.0)
Requires-Dist: torch (==1.10.1)
Requires-Dist: torchaudio (==0.10.1)
Requires-Dist: torchvision (==0.11.2)
Requires-Dist: transformers (>=4.15.0,<5.0.0)
Requires-Dist: xgboost (>=1.5.1,<2.0.0)
